conan_bot/__init__.py
conan_bot/bot.py
conan_bot/config.py
conan_bot-1.0.2.dist-info/LICENSE
conan_bot-1.0.2.dist-info/METADATA
conan_bot-1.0.2.dist-info/WHEEL
conan_bot-1.0.2.dist-info/entry_points.txt
conan_bot-1.0.2.dist-info/top_level.txt
conan_bot-1.0.2.dist-info/RECORD
