Metadata-Version: 2.1
Name: conan-bot
Version: 1.0.2
Summary: Bot for reporting conan exiles information on discord
Home-page: https://github.com/nerakhon/conan-bot
Author: Jan Paul
Author-email: paulj@nerakhon.cz
License: MIT
Platform: UNKNOWN
Classifier: Programming Language :: Python :: 3
Classifier: License :: OSI Approved :: MIT License
Classifier: Operating System :: OS Independent
Requires-Python: >=3.6
Requires-Dist: discord
Requires-Dist: python-a2s
